azulejo/__init__.py
azulejo/analysis.py
azulejo/common.py
azulejo/core.py
azulejo/examples/glycine7/do_glycine7.sh
azulejo/examples/glycine7/info.toml
azulejo/hash.py
azulejo/homology.py
azulejo/ingest.py
azulejo/installer.py
azulejo/installer_data/blast-longids/blast_longer_ids.patch
azulejo/installer_data/blast-longids/disable-testsuite-compilation.txt
azulejo/installer_data/blast-longids/linux/configure_settings.patch
azulejo/installer_data/blast-longids/macos/configure_settings.patch
azulejo/installer_data/dagchainer-tool/dagchainer-0206008.patch
azulejo/installer_data/dagchainer-tool/dagchainer-tool.sh
azulejo/installer_data/dagchainer-tool/downfilter_fasta.sh
azulejo/installer_data/dagchainer-tool/hash_into_fasta_id.pl
azulejo/installer_data/dagchainer-tool/join_homology_synteny.py
azulejo/installer_data/dagchainer-tool/pairs_to_adjacency.py
azulejo/installer_data/dagchainer-tool/top_blast_hit.awk
azulejo/installer_data/mmseqs/linux/mmseqs-azulejo-config.cmake
azulejo/installer_data/mmseqs/macos/mmseqs-azulejo-config.cmake
azulejo/installer_data/muscle/benchmark.fa
azulejo/installer_data/muscle/infinity_fix.patch
azulejo/installer_data/muscle/linux/Makefile
azulejo/installer_data/muscle/macos/Makefile
azulejo/installer_data/usearch/LICENSE.txt
azulejo/installer_data/usearch/linux/Makefile
azulejo/installer_data/usearch/macos/Makefile
azulejo/mailboxes.py
azulejo/merger.py
azulejo/parquet.py
azulejo/protein.py
azulejo/proxy.py
azulejo/synteny.py
azulejo/taxonomy.py
azulejo-0.10.1.dist-info/entry_points.txt
azulejo-0.10.1.dist-info/LICENSE.ncgr
azulejo-0.10.1.dist-info/LICENSE
azulejo-0.10.1.dist-info/WHEEL
azulejo-0.10.1.dist-info/METADATA
azulejo-0.10.1.dist-info/RECORD
