Metadata-Version: 2.1
Name: azulejo
Version: 0.10.1
Summary: tile phylogenetic space with subtrees
Home-page: https://github.com/joelb123/azulejo
License: BSD-3-Clause
Keywords: science,biology,bioinformatics,genomics,data science,phylogeny,protein,sequences,FASTA,GFF
Author: Joel Berendzen
Author-email: joel@generisbio.com
Requires-Python: >=3.7,<4.0
Classifier: Development Status :: 5 - Production/Stable
Classifier: Environment :: Console
Classifier: Intended Audience :: Science/Research
Classifier: License :: OSI Approved :: BSD License
Classifier: Natural Language :: English
Classifier: Operating System :: OS Independent
Classifier: Programming Language :: C
Classifier: Programming Language :: Python :: 3
Classifier: Programming Language :: Python :: 3.7
Classifier: Programming Language :: Python :: 3.8
Classifier: Programming Language :: Python :: 3.9
Classifier: Topic :: Scientific/Engineering :: Bio-Informatics
Requires-Dist: amas (>=1.0,<2.0)
Requires-Dist: attrs
Requires-Dist: beautifulsoup4 (>=4.9.3,<5.0.0)
Requires-Dist: biopython (>=1.78,<2.0)
Requires-Dist: click (>=7.1.2,<8.0.0)
Requires-Dist: click_loguru (>=1.3.0,<2.0.0)
Requires-Dist: click_plugins (>=1.1.1,<2.0.0)
Requires-Dist: dask[bag] (>=2.15.0,<3.0.0)
Requires-Dist: fastaq (>=0.30,<0.31)
Requires-Dist: gffpandas-jb (>=1.2.1.1,<2.0.0.0)
Requires-Dist: matplotlib (>=3.2.1,<4.0.0)
Requires-Dist: memory-tempfile (>=2.2.3,<3.0.0)
Requires-Dist: networkx (>=2.4,<3.0)
Requires-Dist: numpy (>=1.18.3,<2.0.0)
Requires-Dist: packaging (>=20.7,<21.0)
Requires-Dist: pandas (>=1.1.0,<2.0.0)
Requires-Dist: paramiko (>=2.7.1,<3.0.0)
Requires-Dist: pathvalidate (>=2.3.0,<3.0.0)
Requires-Dist: phylopandas (>=0.8.0,<0.9.0)
Requires-Dist: progressbar2 (>=3.53.1,<4.0.0)
Requires-Dist: pyarrow (>=2.0.0,<3.0.0)
Requires-Dist: requests_download (>=0.1.2,<0.2.0)
Requires-Dist: seaborn (>=0.11.0,<0.12.0)
Requires-Dist: sh (>=1.14.1,<2.0.0)
Requires-Dist: smart-open (>=2.0.0,<3.0.0)
Requires-Dist: toml (>=0.10.1,<0.11.0)
Requires-Dist: uri (>=2.0.1,<3.0.0)
Requires-Dist: xxhash (>=2.0.0,<3.0.0)
Project-URL: Documentation, https://azulejo.readthedocs.org
